{
  "sport": "NFL",
  "sportSlug": "nfl",
  "dayBranch": "tomorrow",
  "gameCount": 3,
  "propCount": 117,
  "games": [
    {
      "gameId": "116294",
      "slate": "Early",
      "startTime": "12/25/25 12:00 PM CST",
      "startTimeIso": "2025-12-25T13:00:00.000-05:00",
      "teams": [
        "Dallas Cowboys",
        "Washington Commanders"
      ],
      "propCount": 33,
      "path": "/data/hierarchy/tomorrow/nfl/props-by-game/116294.json"
    },
    {
      "gameId": "116295",
      "slate": "Late",
      "startTime": "12/25/25 03:30 PM CST",
      "startTimeIso": "2025-12-25T16:30:00.000-05:00",
      "teams": [
        "Detroit Lions",
        "Minnesota Vikings"
      ],
      "propCount": 39,
      "path": "/data/hierarchy/tomorrow/nfl/props-by-game/116295.json"
    },
    {
      "gameId": "116466",
      "slate": "Late",
      "startTime": "12/25/25 07:15 PM CST",
      "startTimeIso": "2025-12-25T20:15:00.000-05:00",
      "teams": [
        "Denver Broncos",
        "Kansas City Chiefs"
      ],
      "propCount": 45,
      "path": "/data/hierarchy/tomorrow/nfl/props-by-game/116466.json"
    }
  ],
  "slates": [
    {
      "slate": "early",
      "propCount": 33,
      "path": "/data/hierarchy/tomorrow/nfl/props-by-slate/early.json"
    },
    {
      "slate": "late",
      "propCount": 84,
      "path": "/data/hierarchy/tomorrow/nfl/props-by-slate/late.json"
    }
  ]
}