[
  {
    "propId": "113742_cincinnati-bengals_mitch-tinsley_f2edbe48_receiving-yards",
    "gameId": "113742",
    "playerId": "cincinnati-bengals_mitch-tinsley_f2edbe48",
    "stat": "Receiving Yards",
    "line": 27.5,
    "teamCode": "cincinnati-bengals",
    "opponentCode": "baltimore-ravens",
    "oddsType": "standard",
    "sport": "NFL",
    "startTime": "12/14/25 12:00 PM CST",
    "startTimeIso": "2025-12-14T13:00:00.000-05:00",
    "dayBranch": "tomorrow"
  },
  {
    "propId": "113742_baltimore-ravens_zay-flowers_5e9e5a60_receiving-yards-in-first-2-receptions",
    "gameId": "113742",
    "playerId": "baltimore-ravens_zay-flowers_5e9e5a60",
    "stat": "Receiving Yards in First 2 Receptions",
    "line": 22.5,
    "teamCode": "baltimore-ravens",
    "opponentCode": "cincinnati-bengals",
    "oddsType": "standard",
    "sport": "NFL",
    "startTime": "12/14/25 12:00 PM CST",
    "startTimeIso": "2025-12-14T13:00:00.000-05:00",
    "dayBranch": "tomorrow"
  },
  {
    "propId": "113742_baltimore-ravens_derrick-henry_7473b86f_rush-yards-in-first-5-attempts",
    "gameId": "113742",
    "playerId": "baltimore-ravens_derrick-henry_7473b86f",
    "stat": "Rush Yards in First 5 Attempts",
    "line": 22.5,
    "teamCode": "baltimore-ravens",
    "opponentCode": "cincinnati-bengals",
    "oddsType": "standard",
    "sport": "NFL",
    "startTime": "12/14/25 12:00 PM CST",
    "startTimeIso": "2025-12-14T13:00:00.000-05:00",
    "dayBranch": "tomorrow"
  },
  {
    "propId": "113742_cincinnati-bengals_ja'marr-chase_fe220316_receiving-yards-in-first-2-receptions",
    "gameId": "113742",
    "playerId": "cincinnati-bengals_ja'marr-chase_fe220316",
    "stat": "Receiving Yards in First 2 Receptions",
    "line": 20.5,
    "teamCode": "cincinnati-bengals",
    "opponentCode": "baltimore-ravens",
    "oddsType": "standard",
    "sport": "NFL",
    "startTime": "12/14/25 12:00 PM CST",
    "startTimeIso": "2025-12-14T13:00:00.000-05:00",
    "dayBranch": "tomorrow"
  },
  {
    "propId": "113742_cincinnati-bengals_chase-brown_714f6410_rush-yards-in-first-5-attempts",
    "gameId": "113742",
    "playerId": "cincinnati-bengals_chase-brown_714f6410",
    "stat": "Rush Yards in First 5 Attempts",
    "line": 18.5,
    "teamCode": "cincinnati-bengals",
    "opponentCode": "baltimore-ravens",
    "oddsType": "standard",
    "sport": "NFL",
    "startTime": "12/14/25 12:00 PM CST",
    "startTimeIso": "2025-12-14T13:00:00.000-05:00",
    "dayBranch": "tomorrow"
  },
  {
    "propId": "113742_baltimore-ravens_zay-flowers_5e9e5a60_yards-on-first-reception",
    "gameId": "113742",
    "playerId": "baltimore-ravens_zay-flowers_5e9e5a60",
    "stat": "Yards on First Reception",
    "line": 10.5,
    "teamCode": "baltimore-ravens",
    "opponentCode": "cincinnati-bengals",
    "oddsType": "standard",
    "sport": "NFL",
    "startTime": "12/14/25 12:00 PM CST",
    "startTimeIso": "2025-12-14T13:00:00.000-05:00",
    "dayBranch": "tomorrow"
  },
  {
    "propId": "113742_cincinnati-bengals_ja'marr-chase_fe220316_yards-on-first-reception",
    "gameId": "113742",
    "playerId": "cincinnati-bengals_ja'marr-chase_fe220316",
    "stat": "Yards on First Reception",
    "line": 8.5,
    "teamCode": "cincinnati-bengals",
    "opponentCode": "baltimore-ravens",
    "oddsType": "standard",
    "sport": "NFL",
    "startTime": "12/14/25 12:00 PM CST",
    "startTimeIso": "2025-12-14T13:00:00.000-05:00",
    "dayBranch": "tomorrow"
  },
  {
    "propId": "113742_cincinnati-bengals_joe-burrow_d91bf4dd_pass-yards",
    "gameId": "113742",
    "playerId": "cincinnati-bengals_joe-burrow_d91bf4dd",
    "stat": "Pass Yards",
    "line": 262.5,
    "teamCode": "cincinnati-bengals",
    "opponentCode": "baltimore-ravens",
    "oddsType": "standard",
    "sport": "NFL",
    "startTime": "12/14/25 12:00 PM CST",
    "startTimeIso": "2025-12-14T13:00:00.000-05:00",
    "dayBranch": "tomorrow"
  },
  {
    "propId": "113742_baltimore-ravens_lamar-jackson_cbf71d18_pass-yards",
    "gameId": "113742",
    "playerId": "baltimore-ravens_lamar-jackson_cbf71d18",
    "stat": "Pass Yards",
    "line": 229.5,
    "teamCode": "baltimore-ravens",
    "opponentCode": "cincinnati-bengals",
    "oddsType": "standard",
    "sport": "NFL",
    "startTime": "12/14/25 12:00 PM CST",
    "startTimeIso": "2025-12-14T13:00:00.000-05:00",
    "dayBranch": "tomorrow"
  },
  {
    "propId": "113742_cincinnati-bengals_ja'marr-chase_fe220316_receiving-yards",
    "gameId": "113742",
    "playerId": "cincinnati-bengals_ja'marr-chase_fe220316",
    "stat": "Receiving Yards",
    "line": 90.5,
    "teamCode": "cincinnati-bengals",
    "opponentCode": "baltimore-ravens",
    "oddsType": "standard",
    "sport": "NFL",
    "startTime": "12/14/25 12:00 PM CST",
    "startTimeIso": "2025-12-14T13:00:00.000-05:00",
    "dayBranch": "tomorrow"
  },
  {
    "propId": "113742_baltimore-ravens_derrick-henry_7473b86f_rush-yards",
    "gameId": "113742",
    "playerId": "baltimore-ravens_derrick-henry_7473b86f",
    "stat": "Rush Yards",
    "line": 88.5,
    "teamCode": "baltimore-ravens",
    "opponentCode": "cincinnati-bengals",
    "oddsType": "standard",
    "sport": "NFL",
    "startTime": "12/14/25 12:00 PM CST",
    "startTimeIso": "2025-12-14T13:00:00.000-05:00",
    "dayBranch": "tomorrow"
  },
  {
    "propId": "113742_baltimore-ravens_zay-flowers_5e9e5a60_receiving-yards",
    "gameId": "113742",
    "playerId": "baltimore-ravens_zay-flowers_5e9e5a60",
    "stat": "Receiving Yards",
    "line": 66.5,
    "teamCode": "baltimore-ravens",
    "opponentCode": "cincinnati-bengals",
    "oddsType": "standard",
    "sport": "NFL",
    "startTime": "12/14/25 12:00 PM CST",
    "startTimeIso": "2025-12-14T13:00:00.000-05:00",
    "dayBranch": "tomorrow"
  },
  {
    "propId": "113742_baltimore-ravens_lamar-jackson_cbf71d18_completion-percentage",
    "gameId": "113742",
    "playerId": "baltimore-ravens_lamar-jackson_cbf71d18",
    "stat": "Completion Percentage",
    "line": 65.9,
    "teamCode": "baltimore-ravens",
    "opponentCode": "cincinnati-bengals",
    "oddsType": "standard",
    "sport": "NFL",
    "startTime": "12/14/25 12:00 PM CST",
    "startTimeIso": "2025-12-14T13:00:00.000-05:00",
    "dayBranch": "tomorrow"
  },
  {
    "propId": "113742_cincinnati-bengals_joe-burrow_d91bf4dd_completion-percentage",
    "gameId": "113742",
    "playerId": "cincinnati-bengals_joe-burrow_d91bf4dd",
    "stat": "Completion Percentage",
    "line": 62.9,
    "teamCode": "cincinnati-bengals",
    "opponentCode": "baltimore-ravens",
    "oddsType": "standard",
    "sport": "NFL",
    "startTime": "12/14/25 12:00 PM CST",
    "startTimeIso": "2025-12-14T13:00:00.000-05:00",
    "dayBranch": "tomorrow"
  },
  {
    "propId": "113742_cincinnati-bengals_chase-brown_714f6410_rush-yards",
    "gameId": "113742",
    "playerId": "cincinnati-bengals_chase-brown_714f6410",
    "stat": "Rush Yards",
    "line": 50.5,
    "teamCode": "cincinnati-bengals",
    "opponentCode": "baltimore-ravens",
    "oddsType": "standard",
    "sport": "NFL",
    "startTime": "12/14/25 12:00 PM CST",
    "startTimeIso": "2025-12-14T13:00:00.000-05:00",
    "dayBranch": "tomorrow"
  },
  {
    "propId": "113742_baltimore-ravens_mark-andrews_8e307d07_receiving-yards",
    "gameId": "113742",
    "playerId": "baltimore-ravens_mark-andrews_8e307d07",
    "stat": "Receiving Yards",
    "line": 39.5,
    "teamCode": "baltimore-ravens",
    "opponentCode": "cincinnati-bengals",
    "oddsType": "standard",
    "sport": "NFL",
    "startTime": "12/14/25 12:00 PM CST",
    "startTimeIso": "2025-12-14T13:00:00.000-05:00",
    "dayBranch": "tomorrow"
  },
  {
    "propId": "113742_cincinnati-bengals_mike-gesicki_22b870cd_receiving-yards",
    "gameId": "113742",
    "playerId": "cincinnati-bengals_mike-gesicki_22b870cd",
    "stat": "Receiving Yards",
    "line": 39.5,
    "teamCode": "cincinnati-bengals",
    "opponentCode": "baltimore-ravens",
    "oddsType": "standard",
    "sport": "NFL",
    "startTime": "12/14/25 12:00 PM CST",
    "startTimeIso": "2025-12-14T13:00:00.000-05:00",
    "dayBranch": "tomorrow"
  },
  {
    "propId": "113742_baltimore-ravens_isaiah-likely_507c976a_receiving-yards",
    "gameId": "113742",
    "playerId": "baltimore-ravens_isaiah-likely_507c976a",
    "stat": "Receiving Yards",
    "line": 38.5,
    "teamCode": "baltimore-ravens",
    "opponentCode": "cincinnati-bengals",
    "oddsType": "standard",
    "sport": "NFL",
    "startTime": "12/14/25 12:00 PM CST",
    "startTimeIso": "2025-12-14T13:00:00.000-05:00",
    "dayBranch": "tomorrow"
  },
  {
    "propId": "113742_cincinnati-bengals_joe-burrow_d91bf4dd_pass-attempts",
    "gameId": "113742",
    "playerId": "cincinnati-bengals_joe-burrow_d91bf4dd",
    "stat": "Pass Attempts",
    "line": 37.0,
    "teamCode": "cincinnati-bengals",
    "opponentCode": "baltimore-ravens",
    "oddsType": "standard",
    "sport": "NFL",
    "startTime": "12/14/25 12:00 PM CST",
    "startTimeIso": "2025-12-14T13:00:00.000-05:00",
    "dayBranch": "tomorrow"
  },
  {
    "propId": "113742_cincinnati-bengals_joe-burrow_d91bf4dd_longest-completion",
    "gameId": "113742",
    "playerId": "cincinnati-bengals_joe-burrow_d91bf4dd",
    "stat": "Longest Completion",
    "line": 36.5,
    "teamCode": "cincinnati-bengals",
    "opponentCode": "baltimore-ravens",
    "oddsType": "standard",
    "sport": "NFL",
    "startTime": "12/14/25 12:00 PM CST",
    "startTimeIso": "2025-12-14T13:00:00.000-05:00",
    "dayBranch": "tomorrow"
  },
  {
    "propId": "113742_baltimore-ravens_lamar-jackson_cbf71d18_longest-completion",
    "gameId": "113742",
    "playerId": "baltimore-ravens_lamar-jackson_cbf71d18",
    "stat": "Longest Completion",
    "line": 36.5,
    "teamCode": "baltimore-ravens",
    "opponentCode": "cincinnati-bengals",
    "oddsType": "standard",
    "sport": "NFL",
    "startTime": "12/14/25 12:00 PM CST",
    "startTimeIso": "2025-12-14T13:00:00.000-05:00",
    "dayBranch": "tomorrow"
  },
  {
    "propId": "113742_baltimore-ravens_lamar-jackson_cbf71d18_rush-yards",
    "gameId": "113742",
    "playerId": "baltimore-ravens_lamar-jackson_cbf71d18",
    "stat": "Rush Yards",
    "line": 33.5,
    "teamCode": "baltimore-ravens",
    "opponentCode": "cincinnati-bengals",
    "oddsType": "standard",
    "sport": "NFL",
    "startTime": "12/14/25 12:00 PM CST",
    "startTimeIso": "2025-12-14T13:00:00.000-05:00",
    "dayBranch": "tomorrow"
  },
  {
    "propId": "113742_baltimore-ravens_lamar-jackson_cbf71d18_pass-attempts",
    "gameId": "113742",
    "playerId": "baltimore-ravens_lamar-jackson_cbf71d18",
    "stat": "Pass Attempts",
    "line": 29.5,
    "teamCode": "baltimore-ravens",
    "opponentCode": "cincinnati-bengals",
    "oddsType": "standard",
    "sport": "NFL",
    "startTime": "12/14/25 12:00 PM CST",
    "startTimeIso": "2025-12-14T13:00:00.000-05:00",
    "dayBranch": "tomorrow"
  },
  {
    "propId": "113742_cincinnati-bengals_andrei-iosivas_84a741d3_receiving-yards",
    "gameId": "113742",
    "playerId": "cincinnati-bengals_andrei-iosivas_84a741d3",
    "stat": "Receiving Yards",
    "line": 29.5,
    "teamCode": "cincinnati-bengals",
    "opponentCode": "baltimore-ravens",
    "oddsType": "standard",
    "sport": "NFL",
    "startTime": "12/14/25 12:00 PM CST",
    "startTimeIso": "2025-12-14T13:00:00.000-05:00",
    "dayBranch": "tomorrow"
  },
  {
    "propId": "113742_cincinnati-bengals_samaje-perine_4b1e3dae_rush-yards",
    "gameId": "113742",
    "playerId": "cincinnati-bengals_samaje-perine_4b1e3dae",
    "stat": "Rush Yards",
    "line": 26.5,
    "teamCode": "cincinnati-bengals",
    "opponentCode": "baltimore-ravens",
    "oddsType": "standard",
    "sport": "NFL",
    "startTime": "12/14/25 12:00 PM CST",
    "startTimeIso": "2025-12-14T13:00:00.000-05:00",
    "dayBranch": "tomorrow"
  },
  {
    "propId": "113742_cincinnati-bengals_ja'marr-chase_fe220316_longest-reception",
    "gameId": "113742",
    "playerId": "cincinnati-bengals_ja'marr-chase_fe220316",
    "stat": "Longest Reception",
    "line": 25.5,
    "teamCode": "cincinnati-bengals",
    "opponentCode": "baltimore-ravens",
    "oddsType": "standard",
    "sport": "NFL",
    "startTime": "12/14/25 12:00 PM CST",
    "startTimeIso": "2025-12-14T13:00:00.000-05:00",
    "dayBranch": "tomorrow"
  },
  {
    "propId": "113742_baltimore-ravens_zay-flowers_5e9e5a60_longest-reception",
    "gameId": "113742",
    "playerId": "baltimore-ravens_zay-flowers_5e9e5a60",
    "stat": "Longest Reception",
    "line": 24.5,
    "teamCode": "baltimore-ravens",
    "opponentCode": "cincinnati-bengals",
    "oddsType": "standard",
    "sport": "NFL",
    "startTime": "12/14/25 12:00 PM CST",
    "startTimeIso": "2025-12-14T13:00:00.000-05:00",
    "dayBranch": "tomorrow"
  },
  {
    "propId": "113742_cincinnati-bengals_joe-burrow_d91bf4dd_pass-completions",
    "gameId": "113742",
    "playerId": "cincinnati-bengals_joe-burrow_d91bf4dd",
    "stat": "Pass Completions",
    "line": 24.0,
    "teamCode": "cincinnati-bengals",
    "opponentCode": "baltimore-ravens",
    "oddsType": "standard",
    "sport": "NFL",
    "startTime": "12/14/25 12:00 PM CST",
    "startTimeIso": "2025-12-14T13:00:00.000-05:00",
    "dayBranch": "tomorrow"
  },
  {
    "propId": "113742_cincinnati-bengals_chase-brown_714f6410_receiving-yards",
    "gameId": "113742",
    "playerId": "cincinnati-bengals_chase-brown_714f6410",
    "stat": "Receiving Yards",
    "line": 20.5,
    "teamCode": "cincinnati-bengals",
    "opponentCode": "baltimore-ravens",
    "oddsType": "standard",
    "sport": "NFL",
    "startTime": "12/14/25 12:00 PM CST",
    "startTimeIso": "2025-12-14T13:00:00.000-05:00",
    "dayBranch": "tomorrow"
  },
  {
    "propId": "113742_baltimore-ravens_derrick-henry_7473b86f_longest-rush",
    "gameId": "113742",
    "playerId": "baltimore-ravens_derrick-henry_7473b86f",
    "stat": "Longest Rush",
    "line": 19.5,
    "teamCode": "baltimore-ravens",
    "opponentCode": "cincinnati-bengals",
    "oddsType": "standard",
    "sport": "NFL",
    "startTime": "12/14/25 12:00 PM CST",
    "startTimeIso": "2025-12-14T13:00:00.000-05:00",
    "dayBranch": "tomorrow"
  },
  {
    "propId": "113742_baltimore-ravens_rashod-bateman_a3be80bd_receiving-yards",
    "gameId": "113742",
    "playerId": "baltimore-ravens_rashod-bateman_a3be80bd",
    "stat": "Receiving Yards",
    "line": 19.5,
    "teamCode": "baltimore-ravens",
    "opponentCode": "cincinnati-bengals",
    "oddsType": "standard",
    "sport": "NFL",
    "startTime": "12/14/25 12:00 PM CST",
    "startTimeIso": "2025-12-14T13:00:00.000-05:00",
    "dayBranch": "tomorrow"
  },
  {
    "propId": "113742_baltimore-ravens_lamar-jackson_cbf71d18_pass-completions",
    "gameId": "113742",
    "playerId": "baltimore-ravens_lamar-jackson_cbf71d18",
    "stat": "Pass Completions",
    "line": 19.0,
    "teamCode": "baltimore-ravens",
    "opponentCode": "cincinnati-bengals",
    "oddsType": "standard",
    "sport": "NFL",
    "startTime": "12/14/25 12:00 PM CST",
    "startTimeIso": "2025-12-14T13:00:00.000-05:00",
    "dayBranch": "tomorrow"
  },
  {
    "propId": "113742_baltimore-ravens_isaiah-likely_507c976a_longest-reception",
    "gameId": "113742",
    "playerId": "baltimore-ravens_isaiah-likely_507c976a",
    "stat": "Longest Reception",
    "line": 18.5,
    "teamCode": "baltimore-ravens",
    "opponentCode": "cincinnati-bengals",
    "oddsType": "standard",
    "sport": "NFL",
    "startTime": "12/14/25 12:00 PM CST",
    "startTimeIso": "2025-12-14T13:00:00.000-05:00",
    "dayBranch": "tomorrow"
  },
  {
    "propId": "113742_baltimore-ravens_keaton-mitchell_9cb9ef8a_rush-yards",
    "gameId": "113742",
    "playerId": "baltimore-ravens_keaton-mitchell_9cb9ef8a",
    "stat": "Rush Yards",
    "line": 18.5,
    "teamCode": "baltimore-ravens",
    "opponentCode": "cincinnati-bengals",
    "oddsType": "standard",
    "sport": "NFL",
    "startTime": "12/14/25 12:00 PM CST",
    "startTimeIso": "2025-12-14T13:00:00.000-05:00",
    "dayBranch": "tomorrow"
  },
  {
    "propId": "113742_baltimore-ravens_derrick-henry_7473b86f_rush-attempts",
    "gameId": "113742",
    "playerId": "baltimore-ravens_derrick-henry_7473b86f",
    "stat": "Rush Attempts",
    "line": 17.5,
    "teamCode": "baltimore-ravens",
    "opponentCode": "cincinnati-bengals",
    "oddsType": "standard",
    "sport": "NFL",
    "startTime": "12/14/25 12:00 PM CST",
    "startTimeIso": "2025-12-14T13:00:00.000-05:00",
    "dayBranch": "tomorrow"
  },
  {
    "propId": "113742_baltimore-ravens_mark-andrews_8e307d07_longest-reception",
    "gameId": "113742",
    "playerId": "baltimore-ravens_mark-andrews_8e307d07",
    "stat": "Longest Reception",
    "line": 17.5,
    "teamCode": "baltimore-ravens",
    "opponentCode": "cincinnati-bengals",
    "oddsType": "standard",
    "sport": "NFL",
    "startTime": "12/14/25 12:00 PM CST",
    "startTimeIso": "2025-12-14T13:00:00.000-05:00",
    "dayBranch": "tomorrow"
  },
  {
    "propId": "113742_baltimore-ravens_deandre-hopkins_adffd331_receiving-yards",
    "gameId": "113742",
    "playerId": "baltimore-ravens_deandre-hopkins_adffd331",
    "stat": "Receiving Yards",
    "line": 16.5,
    "teamCode": "baltimore-ravens",
    "opponentCode": "cincinnati-bengals",
    "oddsType": "standard",
    "sport": "NFL",
    "startTime": "12/14/25 12:00 PM CST",
    "startTimeIso": "2025-12-14T13:00:00.000-05:00",
    "dayBranch": "tomorrow"
  },
  {
    "propId": "113742_cincinnati-bengals_andrei-iosivas_84a741d3_longest-reception",
    "gameId": "113742",
    "playerId": "cincinnati-bengals_andrei-iosivas_84a741d3",
    "stat": "Longest Reception",
    "line": 15.5,
    "teamCode": "cincinnati-bengals",
    "opponentCode": "baltimore-ravens",
    "oddsType": "standard",
    "sport": "NFL",
    "startTime": "12/14/25 12:00 PM CST",
    "startTimeIso": "2025-12-14T13:00:00.000-05:00",
    "dayBranch": "tomorrow"
  },
  {
    "propId": "113742_baltimore-ravens_lamar-jackson_cbf71d18_longest-rush",
    "gameId": "113742",
    "playerId": "baltimore-ravens_lamar-jackson_cbf71d18",
    "stat": "Longest Rush",
    "line": 13.5,
    "teamCode": "baltimore-ravens",
    "opponentCode": "cincinnati-bengals",
    "oddsType": "standard",
    "sport": "NFL",
    "startTime": "12/14/25 12:00 PM CST",
    "startTimeIso": "2025-12-14T13:00:00.000-05:00",
    "dayBranch": "tomorrow"
  },
  {
    "propId": "113742_baltimore-ravens_deandre-hopkins_adffd331_longest-reception",
    "gameId": "113742",
    "playerId": "baltimore-ravens_deandre-hopkins_adffd331",
    "stat": "Longest Reception",
    "line": 13.5,
    "teamCode": "baltimore-ravens",
    "opponentCode": "cincinnati-bengals",
    "oddsType": "standard",
    "sport": "NFL",
    "startTime": "12/14/25 12:00 PM CST",
    "startTimeIso": "2025-12-14T13:00:00.000-05:00",
    "dayBranch": "tomorrow"
  },
  {
    "propId": "113742_baltimore-ravens_rashod-bateman_a3be80bd_longest-reception",
    "gameId": "113742",
    "playerId": "baltimore-ravens_rashod-bateman_a3be80bd",
    "stat": "Longest Reception",
    "line": 13.5,
    "teamCode": "baltimore-ravens",
    "opponentCode": "cincinnati-bengals",
    "oddsType": "standard",
    "sport": "NFL",
    "startTime": "12/14/25 12:00 PM CST",
    "startTimeIso": "2025-12-14T13:00:00.000-05:00",
    "dayBranch": "tomorrow"
  },
  {
    "propId": "113742_cincinnati-bengals_chase-brown_714f6410_longest-rush",
    "gameId": "113742",
    "playerId": "cincinnati-bengals_chase-brown_714f6410",
    "stat": "Longest Rush",
    "line": 12.5,
    "teamCode": "cincinnati-bengals",
    "opponentCode": "baltimore-ravens",
    "oddsType": "standard",
    "sport": "NFL",
    "startTime": "12/14/25 12:00 PM CST",
    "startTimeIso": "2025-12-14T13:00:00.000-05:00",
    "dayBranch": "tomorrow"
  },
  {
    "propId": "113742_cincinnati-bengals_chase-brown_714f6410_rush-attempts",
    "gameId": "113742",
    "playerId": "cincinnati-bengals_chase-brown_714f6410",
    "stat": "Rush Attempts",
    "line": 12.5,
    "teamCode": "cincinnati-bengals",
    "opponentCode": "baltimore-ravens",
    "oddsType": "standard",
    "sport": "NFL",
    "startTime": "12/14/25 12:00 PM CST",
    "startTimeIso": "2025-12-14T13:00:00.000-05:00",
    "dayBranch": "tomorrow"
  },
  {
    "propId": "113742_cincinnati-bengals_noah-fant_99fb335a_receiving-yards",
    "gameId": "113742",
    "playerId": "cincinnati-bengals_noah-fant_99fb335a",
    "stat": "Receiving Yards",
    "line": 11.5,
    "teamCode": "cincinnati-bengals",
    "opponentCode": "baltimore-ravens",
    "oddsType": "standard",
    "sport": "NFL",
    "startTime": "12/14/25 12:00 PM CST",
    "startTimeIso": "2025-12-14T13:00:00.000-05:00",
    "dayBranch": "tomorrow"
  },
  {
    "propId": "113742_cincinnati-bengals_ja'marr-chase_fe220316_rec-targets",
    "gameId": "113742",
    "playerId": "cincinnati-bengals_ja'marr-chase_fe220316",
    "stat": "Rec Targets",
    "line": 11.0,
    "teamCode": "cincinnati-bengals",
    "opponentCode": "baltimore-ravens",
    "oddsType": "standard",
    "sport": "NFL",
    "startTime": "12/14/25 12:00 PM CST",
    "startTimeIso": "2025-12-14T13:00:00.000-05:00",
    "dayBranch": "tomorrow"
  },
  {
    "propId": "113742_cincinnati-bengals_chase-brown_714f6410_longest-reception",
    "gameId": "113742",
    "playerId": "cincinnati-bengals_chase-brown_714f6410",
    "stat": "Longest Reception",
    "line": 10.5,
    "teamCode": "cincinnati-bengals",
    "opponentCode": "baltimore-ravens",
    "oddsType": "standard",
    "sport": "NFL",
    "startTime": "12/14/25 12:00 PM CST",
    "startTimeIso": "2025-12-14T13:00:00.000-05:00",
    "dayBranch": "tomorrow"
  },
  {
    "propId": "113742_cincinnati-bengals_samaje-perine_4b1e3dae_longest-rush",
    "gameId": "113742",
    "playerId": "cincinnati-bengals_samaje-perine_4b1e3dae",
    "stat": "Longest Rush",
    "line": 10.5,
    "teamCode": "cincinnati-bengals",
    "opponentCode": "baltimore-ravens",
    "oddsType": "standard",
    "sport": "NFL",
    "startTime": "12/14/25 12:00 PM CST",
    "startTimeIso": "2025-12-14T13:00:00.000-05:00",
    "dayBranch": "tomorrow"
  },
  {
    "propId": "113742_baltimore-ravens_derrick-henry_7473b86f_receiving-yards",
    "gameId": "113742",
    "playerId": "baltimore-ravens_derrick-henry_7473b86f",
    "stat": "Receiving Yards",
    "line": 9.5,
    "teamCode": "baltimore-ravens",
    "opponentCode": "cincinnati-bengals",
    "oddsType": "standard",
    "sport": "NFL",
    "startTime": "12/14/25 12:00 PM CST",
    "startTimeIso": "2025-12-14T13:00:00.000-05:00",
    "dayBranch": "tomorrow"
  },
  {
    "propId": "113742_cincinnati-bengals_noah-fant_99fb335a_longest-reception",
    "gameId": "113742",
    "playerId": "cincinnati-bengals_noah-fant_99fb335a",
    "stat": "Longest Reception",
    "line": 8.5,
    "teamCode": "cincinnati-bengals",
    "opponentCode": "baltimore-ravens",
    "oddsType": "standard",
    "sport": "NFL",
    "startTime": "12/14/25 12:00 PM CST",
    "startTimeIso": "2025-12-14T13:00:00.000-05:00",
    "dayBranch": "tomorrow"
  },
  {
    "propId": "113742_baltimore-ravens_keaton-mitchell_9cb9ef8a_longest-rush",
    "gameId": "113742",
    "playerId": "baltimore-ravens_keaton-mitchell_9cb9ef8a",
    "stat": "Longest Rush",
    "line": 8.5,
    "teamCode": "baltimore-ravens",
    "opponentCode": "cincinnati-bengals",
    "oddsType": "standard",
    "sport": "NFL",
    "startTime": "12/14/25 12:00 PM CST",
    "startTimeIso": "2025-12-14T13:00:00.000-05:00",
    "dayBranch": "tomorrow"
  },
  {
    "propId": "113742_baltimore-ravens_zay-flowers_5e9e5a60_rec-targets",
    "gameId": "113742",
    "playerId": "baltimore-ravens_zay-flowers_5e9e5a60",
    "stat": "Rec Targets",
    "line": 8.0,
    "teamCode": "baltimore-ravens",
    "opponentCode": "cincinnati-bengals",
    "oddsType": "standard",
    "sport": "NFL",
    "startTime": "12/14/25 12:00 PM CST",
    "startTimeIso": "2025-12-14T13:00:00.000-05:00",
    "dayBranch": "tomorrow"
  },
  {
    "propId": "113742_cincinnati-bengals_ja'marr-chase_fe220316_receptions",
    "gameId": "113742",
    "playerId": "cincinnati-bengals_ja'marr-chase_fe220316",
    "stat": "Receptions",
    "line": 7.5,
    "teamCode": "cincinnati-bengals",
    "opponentCode": "baltimore-ravens",
    "oddsType": "standard",
    "sport": "NFL",
    "startTime": "12/14/25 12:00 PM CST",
    "startTimeIso": "2025-12-14T13:00:00.000-05:00",
    "dayBranch": "tomorrow"
  },
  {
    "propId": "113742_baltimore-ravens_tyler-loop_4c98301a_kicking-points",
    "gameId": "113742",
    "playerId": "baltimore-ravens_tyler-loop_4c98301a",
    "stat": "Kicking Points",
    "line": 7.5,
    "teamCode": "baltimore-ravens",
    "opponentCode": "cincinnati-bengals",
    "oddsType": "standard",
    "sport": "NFL",
    "startTime": "12/14/25 12:00 PM CST",
    "startTimeIso": "2025-12-14T13:00:00.000-05:00",
    "dayBranch": "tomorrow"
  },
  {
    "propId": "113742_cincinnati-bengals_evan-mcpherson_1a56c3e2_kicking-points",
    "gameId": "113742",
    "playerId": "cincinnati-bengals_evan-mcpherson_1a56c3e2",
    "stat": "Kicking Points",
    "line": 7.0,
    "teamCode": "cincinnati-bengals",
    "opponentCode": "baltimore-ravens",
    "oddsType": "standard",
    "sport": "NFL",
    "startTime": "12/14/25 12:00 PM CST",
    "startTimeIso": "2025-12-14T13:00:00.000-05:00",
    "dayBranch": "tomorrow"
  },
  {
    "propId": "113742_baltimore-ravens_lamar-jackson_cbf71d18_rush-attempts",
    "gameId": "113742",
    "playerId": "baltimore-ravens_lamar-jackson_cbf71d18",
    "stat": "Rush Attempts",
    "line": 6.5,
    "teamCode": "baltimore-ravens",
    "opponentCode": "cincinnati-bengals",
    "oddsType": "standard",
    "sport": "NFL",
    "startTime": "12/14/25 12:00 PM CST",
    "startTimeIso": "2025-12-14T13:00:00.000-05:00",
    "dayBranch": "tomorrow"
  },
  {
    "propId": "113742_baltimore-ravens_derrick-henry_7473b86f_longest-reception",
    "gameId": "113742",
    "playerId": "baltimore-ravens_derrick-henry_7473b86f",
    "stat": "Longest Reception",
    "line": 6.5,
    "teamCode": "baltimore-ravens",
    "opponentCode": "cincinnati-bengals",
    "oddsType": "standard",
    "sport": "NFL",
    "startTime": "12/14/25 12:00 PM CST",
    "startTimeIso": "2025-12-14T13:00:00.000-05:00",
    "dayBranch": "tomorrow"
  },
  {
    "propId": "113742_cincinnati-bengals_tanner-hudson_2f9bcf8f_receiving-yards",
    "gameId": "113742",
    "playerId": "cincinnati-bengals_tanner-hudson_2f9bcf8f",
    "stat": "Receiving Yards",
    "line": 5.5,
    "teamCode": "cincinnati-bengals",
    "opponentCode": "baltimore-ravens",
    "oddsType": "standard",
    "sport": "NFL",
    "startTime": "12/14/25 12:00 PM CST",
    "startTimeIso": "2025-12-14T13:00:00.000-05:00",
    "dayBranch": "tomorrow"
  },
  {
    "propId": "113742_cincinnati-bengals_joe-burrow_d91bf4dd_rush-yards",
    "gameId": "113742",
    "playerId": "cincinnati-bengals_joe-burrow_d91bf4dd",
    "stat": "Rush Yards",
    "line": 5.5,
    "teamCode": "cincinnati-bengals",
    "opponentCode": "baltimore-ravens",
    "oddsType": "standard",
    "sport": "NFL",
    "startTime": "12/14/25 12:00 PM CST",
    "startTimeIso": "2025-12-14T13:00:00.000-05:00",
    "dayBranch": "tomorrow"
  },
  {
    "propId": "113742_cincinnati-bengals_mike-gesicki_22b870cd_rec-targets",
    "gameId": "113742",
    "playerId": "cincinnati-bengals_mike-gesicki_22b870cd",
    "stat": "Rec Targets",
    "line": 5.5,
    "teamCode": "cincinnati-bengals",
    "opponentCode": "baltimore-ravens",
    "oddsType": "standard",
    "sport": "NFL",
    "startTime": "12/14/25 12:00 PM CST",
    "startTimeIso": "2025-12-14T13:00:00.000-05:00",
    "dayBranch": "tomorrow"
  },
  {
    "propId": "113742_baltimore-ravens_rasheen-ali_e6d7b8ce_receiving-yards",
    "gameId": "113742",
    "playerId": "baltimore-ravens_rasheen-ali_e6d7b8ce",
    "stat": "Receiving Yards",
    "line": 5.5,
    "teamCode": "baltimore-ravens",
    "opponentCode": "cincinnati-bengals",
    "oddsType": "standard",
    "sport": "NFL",
    "startTime": "12/14/25 12:00 PM CST",
    "startTimeIso": "2025-12-14T13:00:00.000-05:00",
    "dayBranch": "tomorrow"
  },
  {
    "propId": "113742_baltimore-ravens_rasheen-ali_e6d7b8ce_longest-reception",
    "gameId": "113742",
    "playerId": "baltimore-ravens_rasheen-ali_e6d7b8ce",
    "stat": "Longest Reception",
    "line": 5.5,
    "teamCode": "baltimore-ravens",
    "opponentCode": "cincinnati-bengals",
    "oddsType": "standard",
    "sport": "NFL",
    "startTime": "12/14/25 12:00 PM CST",
    "startTimeIso": "2025-12-14T13:00:00.000-05:00",
    "dayBranch": "tomorrow"
  },
  {
    "propId": "113742_baltimore-ravens_zay-flowers_5e9e5a60_receptions",
    "gameId": "113742",
    "playerId": "baltimore-ravens_zay-flowers_5e9e5a60",
    "stat": "Receptions",
    "line": 5.0,
    "teamCode": "baltimore-ravens",
    "opponentCode": "cincinnati-bengals",
    "oddsType": "standard",
    "sport": "NFL",
    "startTime": "12/14/25 12:00 PM CST",
    "startTimeIso": "2025-12-14T13:00:00.000-05:00",
    "dayBranch": "tomorrow"
  },
  {
    "propId": "113742_baltimore-ravens_mark-andrews_8e307d07_rec-targets",
    "gameId": "113742",
    "playerId": "baltimore-ravens_mark-andrews_8e307d07",
    "stat": "Rec Targets",
    "line": 5.0,
    "teamCode": "baltimore-ravens",
    "opponentCode": "cincinnati-bengals",
    "oddsType": "standard",
    "sport": "NFL",
    "startTime": "12/14/25 12:00 PM CST",
    "startTimeIso": "2025-12-14T13:00:00.000-05:00",
    "dayBranch": "tomorrow"
  },
  {
    "propId": "113742_cincinnati-bengals_joe-burrow_d91bf4dd_longest-rush",
    "gameId": "113742",
    "playerId": "cincinnati-bengals_joe-burrow_d91bf4dd",
    "stat": "Longest Rush",
    "line": 4.5,
    "teamCode": "cincinnati-bengals",
    "opponentCode": "baltimore-ravens",
    "oddsType": "standard",
    "sport": "NFL",
    "startTime": "12/14/25 12:00 PM CST",
    "startTimeIso": "2025-12-14T13:00:00.000-05:00",
    "dayBranch": "tomorrow"
  },
  {
    "propId": "113742_baltimore-ravens_roquan-smith_11c1273a_assists",
    "gameId": "113742",
    "playerId": "baltimore-ravens_roquan-smith_11c1273a",
    "stat": "Assists",
    "line": 4.5,
    "teamCode": "baltimore-ravens",
    "opponentCode": "cincinnati-bengals",
    "oddsType": "standard",
    "sport": "NFL",
    "startTime": "12/14/25 12:00 PM CST",
    "startTimeIso": "2025-12-14T13:00:00.000-05:00",
    "dayBranch": "tomorrow"
  },
  {
    "propId": "113742_cincinnati-bengals_samaje-perine_4b1e3dae_longest-reception",
    "gameId": "113742",
    "playerId": "cincinnati-bengals_samaje-perine_4b1e3dae",
    "stat": "Longest Reception",
    "line": 4.5,
    "teamCode": "cincinnati-bengals",
    "opponentCode": "baltimore-ravens",
    "oddsType": "standard",
    "sport": "NFL",
    "startTime": "12/14/25 12:00 PM CST",
    "startTimeIso": "2025-12-14T13:00:00.000-05:00",
    "dayBranch": "tomorrow"
  },
  {
    "propId": "113742_cincinnati-bengals_samaje-perine_4b1e3dae_receiving-yards",
    "gameId": "113742",
    "playerId": "cincinnati-bengals_samaje-perine_4b1e3dae",
    "stat": "Receiving Yards",
    "line": 4.5,
    "teamCode": "cincinnati-bengals",
    "opponentCode": "baltimore-ravens",
    "oddsType": "standard",
    "sport": "NFL",
    "startTime": "12/14/25 12:00 PM CST",
    "startTimeIso": "2025-12-14T13:00:00.000-05:00",
    "dayBranch": "tomorrow"
  },
  {
    "propId": "113742_cincinnati-bengals_chase-brown_714f6410_rec-targets",
    "gameId": "113742",
    "playerId": "cincinnati-bengals_chase-brown_714f6410",
    "stat": "Rec Targets",
    "line": 4.5,
    "teamCode": "cincinnati-bengals",
    "opponentCode": "baltimore-ravens",
    "oddsType": "standard",
    "sport": "NFL",
    "startTime": "12/14/25 12:00 PM CST",
    "startTimeIso": "2025-12-14T13:00:00.000-05:00",
    "dayBranch": "tomorrow"
  },
  {
    "propId": "113742_cincinnati-bengals_andrei-iosivas_84a741d3_rec-targets",
    "gameId": "113742",
    "playerId": "cincinnati-bengals_andrei-iosivas_84a741d3",
    "stat": "Rec Targets",
    "line": 4.5,
    "teamCode": "cincinnati-bengals",
    "opponentCode": "baltimore-ravens",
    "oddsType": "standard",
    "sport": "NFL",
    "startTime": "12/14/25 12:00 PM CST",
    "startTimeIso": "2025-12-14T13:00:00.000-05:00",
    "dayBranch": "tomorrow"
  },
  {
    "propId": "113742_baltimore-ravens_keaton-mitchell_9cb9ef8a_longest-reception",
    "gameId": "113742",
    "playerId": "baltimore-ravens_keaton-mitchell_9cb9ef8a",
    "stat": "Longest Reception",
    "line": 4.5,
    "teamCode": "baltimore-ravens",
    "opponentCode": "cincinnati-bengals",
    "oddsType": "standard",
    "sport": "NFL",
    "startTime": "12/14/25 12:00 PM CST",
    "startTimeIso": "2025-12-14T13:00:00.000-05:00",
    "dayBranch": "tomorrow"
  },
  {
    "propId": "113742_baltimore-ravens_keaton-mitchell_9cb9ef8a_receiving-yards",
    "gameId": "113742",
    "playerId": "baltimore-ravens_keaton-mitchell_9cb9ef8a",
    "stat": "Receiving Yards",
    "line": 4.5,
    "teamCode": "baltimore-ravens",
    "opponentCode": "cincinnati-bengals",
    "oddsType": "standard",
    "sport": "NFL",
    "startTime": "12/14/25 12:00 PM CST",
    "startTimeIso": "2025-12-14T13:00:00.000-05:00",
    "dayBranch": "tomorrow"
  },
  {
    "propId": "113742_baltimore-ravens_isaiah-likely_507c976a_rec-targets",
    "gameId": "113742",
    "playerId": "baltimore-ravens_isaiah-likely_507c976a",
    "stat": "Rec Targets",
    "line": 4.0,
    "teamCode": "baltimore-ravens",
    "opponentCode": "cincinnati-bengals",
    "oddsType": "standard",
    "sport": "NFL",
    "startTime": "12/14/25 12:00 PM CST",
    "startTimeIso": "2025-12-14T13:00:00.000-05:00",
    "dayBranch": "tomorrow"
  },
  {
    "propId": "113742_cincinnati-bengals_chase-brown_714f6410_yards-on-first-rush-attempt",
    "gameId": "113742",
    "playerId": "cincinnati-bengals_chase-brown_714f6410",
    "stat": "Yards on First Rush Attempt",
    "line": 3.5,
    "teamCode": "cincinnati-bengals",
    "opponentCode": "baltimore-ravens",
    "oddsType": "standard",
    "sport": "NFL",
    "startTime": "12/14/25 12:00 PM CST",
    "startTimeIso": "2025-12-14T13:00:00.000-05:00",
    "dayBranch": "tomorrow"
  },
  {
    "propId": "113742_cincinnati-bengals_chase-brown_714f6410_receptions",
    "gameId": "113742",
    "playerId": "cincinnati-bengals_chase-brown_714f6410",
    "stat": "Receptions",
    "line": 3.5,
    "teamCode": "cincinnati-bengals",
    "opponentCode": "baltimore-ravens",
    "oddsType": "standard",
    "sport": "NFL",
    "startTime": "12/14/25 12:00 PM CST",
    "startTimeIso": "2025-12-14T13:00:00.000-05:00",
    "dayBranch": "tomorrow"
  },
  {
    "propId": "113742_baltimore-ravens_mark-andrews_8e307d07_receptions",
    "gameId": "113742",
    "playerId": "baltimore-ravens_mark-andrews_8e307d07",
    "stat": "Receptions",
    "line": 3.5,
    "teamCode": "baltimore-ravens",
    "opponentCode": "cincinnati-bengals",
    "oddsType": "standard",
    "sport": "NFL",
    "startTime": "12/14/25 12:00 PM CST",
    "startTimeIso": "2025-12-14T13:00:00.000-05:00",
    "dayBranch": "tomorrow"
  },
  {
    "propId": "113742_cincinnati-bengals_ryan-rehkow_0204232c_punts",
    "gameId": "113742",
    "playerId": "cincinnati-bengals_ryan-rehkow_0204232c",
    "stat": "Punts",
    "line": 3.5,
    "teamCode": "cincinnati-bengals",
    "opponentCode": "baltimore-ravens",
    "oddsType": "standard",
    "sport": "NFL",
    "startTime": "12/14/25 12:00 PM CST",
    "startTimeIso": "2025-12-14T13:00:00.000-05:00",
    "dayBranch": "tomorrow"
  },
  {
    "propId": "113742_baltimore-ravens_isaiah-likely_507c976a_receptions",
    "gameId": "113742",
    "playerId": "baltimore-ravens_isaiah-likely_507c976a",
    "stat": "Receptions",
    "line": 3.0,
    "teamCode": "baltimore-ravens",
    "opponentCode": "cincinnati-bengals",
    "oddsType": "standard",
    "sport": "NFL",
    "startTime": "12/14/25 12:00 PM CST",
    "startTimeIso": "2025-12-14T13:00:00.000-05:00",
    "dayBranch": "tomorrow"
  },
  {
    "propId": "113742_baltimore-ravens_rashod-bateman_a3be80bd_rec-targets",
    "gameId": "113742",
    "playerId": "baltimore-ravens_rashod-bateman_a3be80bd",
    "stat": "Rec Targets",
    "line": 3.0,
    "teamCode": "baltimore-ravens",
    "opponentCode": "cincinnati-bengals",
    "oddsType": "standard",
    "sport": "NFL",
    "startTime": "12/14/25 12:00 PM CST",
    "startTimeIso": "2025-12-14T13:00:00.000-05:00",
    "dayBranch": "tomorrow"
  },
  {
    "propId": "113742_baltimore-ravens_jordan-stout_cdf41177_punts",
    "gameId": "113742",
    "playerId": "baltimore-ravens_jordan-stout_cdf41177",
    "stat": "Punts",
    "line": 3.0,
    "teamCode": "baltimore-ravens",
    "opponentCode": "cincinnati-bengals",
    "oddsType": "standard",
    "sport": "NFL",
    "startTime": "12/14/25 12:00 PM CST",
    "startTimeIso": "2025-12-14T13:00:00.000-05:00",
    "dayBranch": "tomorrow"
  },
  {
    "propId": "113742_cincinnati-bengals_evan-mcpherson_1a56c3e2_pat-made",
    "gameId": "113742",
    "playerId": "cincinnati-bengals_evan-mcpherson_1a56c3e2",
    "stat": "PAT Made",
    "line": 2.5,
    "teamCode": "cincinnati-bengals",
    "opponentCode": "baltimore-ravens",
    "oddsType": "standard",
    "sport": "NFL",
    "startTime": "12/14/25 12:00 PM CST",
    "startTimeIso": "2025-12-14T13:00:00.000-05:00",
    "dayBranch": "tomorrow"
  },
  {
    "propId": "113742_baltimore-ravens_kyle-hamilton_f7c56112_assists",
    "gameId": "113742",
    "playerId": "baltimore-ravens_kyle-hamilton_f7c56112",
    "stat": "Assists",
    "line": 2.5,
    "teamCode": "baltimore-ravens",
    "opponentCode": "cincinnati-bengals",
    "oddsType": "standard",
    "sport": "NFL",
    "startTime": "12/14/25 12:00 PM CST",
    "startTimeIso": "2025-12-14T13:00:00.000-05:00",
    "dayBranch": "tomorrow"
  },
  {
    "propId": "113742_cincinnati-bengals_andrei-iosivas_84a741d3_receptions",
    "gameId": "113742",
    "playerId": "cincinnati-bengals_andrei-iosivas_84a741d3",
    "stat": "Receptions",
    "line": 2.5,
    "teamCode": "cincinnati-bengals",
    "opponentCode": "baltimore-ravens",
    "oddsType": "standard",
    "sport": "NFL",
    "startTime": "12/14/25 12:00 PM CST",
    "startTimeIso": "2025-12-14T13:00:00.000-05:00",
    "dayBranch": "tomorrow"
  },
  {
    "propId": "113742_baltimore-ravens_zay-flowers_5e9e5a60_rush-yards",
    "gameId": "113742",
    "playerId": "baltimore-ravens_zay-flowers_5e9e5a60",
    "stat": "Rush Yards",
    "line": 2.5,
    "teamCode": "baltimore-ravens",
    "opponentCode": "cincinnati-bengals",
    "oddsType": "standard",
    "sport": "NFL",
    "startTime": "12/14/25 12:00 PM CST",
    "startTimeIso": "2025-12-14T13:00:00.000-05:00",
    "dayBranch": "tomorrow"
  },
  {
    "propId": "113742_baltimore-ravens_deandre-hopkins_adffd331_rec-targets",
    "gameId": "113742",
    "playerId": "baltimore-ravens_deandre-hopkins_adffd331",
    "stat": "Rec Targets",
    "line": 2.0,
    "teamCode": "baltimore-ravens",
    "opponentCode": "cincinnati-bengals",
    "oddsType": "standard",
    "sport": "NFL",
    "startTime": "12/14/25 12:00 PM CST",
    "startTimeIso": "2025-12-14T13:00:00.000-05:00",
    "dayBranch": "tomorrow"
  },
  {
    "propId": "113742_baltimore-ravens_charlie-kolar_5c6eb272_receiving-yards",
    "gameId": "113742",
    "playerId": "baltimore-ravens_charlie-kolar_5c6eb272",
    "stat": "Receiving Yards",
    "line": 1.5,
    "teamCode": "baltimore-ravens",
    "opponentCode": "cincinnati-bengals",
    "oddsType": "standard",
    "sport": "NFL",
    "startTime": "12/14/25 12:00 PM CST",
    "startTimeIso": "2025-12-14T13:00:00.000-05:00",
    "dayBranch": "tomorrow"
  },
  {
    "propId": "113742_cincinnati-bengals_evan-mcpherson_1a56c3e2_fg-made",
    "gameId": "113742",
    "playerId": "cincinnati-bengals_evan-mcpherson_1a56c3e2",
    "stat": "FG Made",
    "line": 1.5,
    "teamCode": "cincinnati-bengals",
    "opponentCode": "baltimore-ravens",
    "oddsType": "standard",
    "sport": "NFL",
    "startTime": "12/14/25 12:00 PM CST",
    "startTimeIso": "2025-12-14T13:00:00.000-05:00",
    "dayBranch": "tomorrow"
  },
  {
    "propId": "113742_baltimore-ravens_tyler-loop_4c98301a_fg-made",
    "gameId": "113742",
    "playerId": "baltimore-ravens_tyler-loop_4c98301a",
    "stat": "FG Made",
    "line": 1.5,
    "teamCode": "baltimore-ravens",
    "opponentCode": "cincinnati-bengals",
    "oddsType": "standard",
    "sport": "NFL",
    "startTime": "12/14/25 12:00 PM CST",
    "startTimeIso": "2025-12-14T13:00:00.000-05:00",
    "dayBranch": "tomorrow"
  },
  {
    "propId": "113742_baltimore-ravens_deandre-hopkins_adffd331_receptions",
    "gameId": "113742",
    "playerId": "baltimore-ravens_deandre-hopkins_adffd331",
    "stat": "Receptions",
    "line": 1.5,
    "teamCode": "baltimore-ravens",
    "opponentCode": "cincinnati-bengals",
    "oddsType": "standard",
    "sport": "NFL",
    "startTime": "12/14/25 12:00 PM CST",
    "startTimeIso": "2025-12-14T13:00:00.000-05:00",
    "dayBranch": "tomorrow"
  },
  {
    "propId": "113742_baltimore-ravens_rashod-bateman_a3be80bd_receptions",
    "gameId": "113742",
    "playerId": "baltimore-ravens_rashod-bateman_a3be80bd",
    "stat": "Receptions",
    "line": 1.5,
    "teamCode": "baltimore-ravens",
    "opponentCode": "cincinnati-bengals",
    "oddsType": "standard",
    "sport": "NFL",
    "startTime": "12/14/25 12:00 PM CST",
    "startTimeIso": "2025-12-14T13:00:00.000-05:00",
    "dayBranch": "tomorrow"
  },
  {
    "propId": "113742_baltimore-ravens_derrick-henry_7473b86f_rec-targets",
    "gameId": "113742",
    "playerId": "baltimore-ravens_derrick-henry_7473b86f",
    "stat": "Rec Targets",
    "line": 1.5,
    "teamCode": "baltimore-ravens",
    "opponentCode": "cincinnati-bengals",
    "oddsType": "standard",
    "sport": "NFL",
    "startTime": "12/14/25 12:00 PM CST",
    "startTimeIso": "2025-12-14T13:00:00.000-05:00",
    "dayBranch": "tomorrow"
  },
  {
    "propId": "113742_baltimore-ravens_marlon-humphrey_845af5be_assists",
    "gameId": "113742",
    "playerId": "baltimore-ravens_marlon-humphrey_845af5be",
    "stat": "Assists",
    "line": 1.5,
    "teamCode": "baltimore-ravens",
    "opponentCode": "cincinnati-bengals",
    "oddsType": "standard",
    "sport": "NFL",
    "startTime": "12/14/25 12:00 PM CST",
    "startTimeIso": "2025-12-14T13:00:00.000-05:00",
    "dayBranch": "tomorrow"
  },
  {
    "propId": "113742_cincinnati-bengals_noah-fant_99fb335a_receptions",
    "gameId": "113742",
    "playerId": "cincinnati-bengals_noah-fant_99fb335a",
    "stat": "Receptions",
    "line": 1.5,
    "teamCode": "cincinnati-bengals",
    "opponentCode": "baltimore-ravens",
    "oddsType": "standard",
    "sport": "NFL",
    "startTime": "12/14/25 12:00 PM CST",
    "startTimeIso": "2025-12-14T13:00:00.000-05:00",
    "dayBranch": "tomorrow"
  },
  {
    "propId": "113742_cincinnati-bengals_joseph-ossai_745372ec_assists",
    "gameId": "113742",
    "playerId": "cincinnati-bengals_joseph-ossai_745372ec",
    "stat": "Assists",
    "line": 1.5,
    "teamCode": "cincinnati-bengals",
    "opponentCode": "baltimore-ravens",
    "oddsType": "standard",
    "sport": "NFL",
    "startTime": "12/14/25 12:00 PM CST",
    "startTimeIso": "2025-12-14T13:00:00.000-05:00",
    "dayBranch": "tomorrow"
  },
  {
    "propId": "113742_cincinnati-bengals_myles-murphy_65d2301a_assists",
    "gameId": "113742",
    "playerId": "cincinnati-bengals_myles-murphy_65d2301a",
    "stat": "Assists",
    "line": 1.5,
    "teamCode": "cincinnati-bengals",
    "opponentCode": "baltimore-ravens",
    "oddsType": "standard",
    "sport": "NFL",
    "startTime": "12/14/25 12:00 PM CST",
    "startTimeIso": "2025-12-14T13:00:00.000-05:00",
    "dayBranch": "tomorrow"
  },
  {
    "propId": "113742_cincinnati-bengals_joe-burrow_d91bf4dd_int",
    "gameId": "113742",
    "playerId": "cincinnati-bengals_joe-burrow_d91bf4dd",
    "stat": "INT",
    "line": 0.5,
    "teamCode": "cincinnati-bengals",
    "opponentCode": "baltimore-ravens",
    "oddsType": "standard",
    "sport": "NFL",
    "startTime": "12/14/25 12:00 PM CST",
    "startTimeIso": "2025-12-14T13:00:00.000-05:00",
    "dayBranch": "tomorrow"
  }
]